{
    "os": "Linux-5.15.0-89-generic-x86_64-with-glibc2.31",
    "python": "3.10.13",
    "heartbeatAt": "2024-02-01T18:33:16.115552",
    "startedAt": "2024-02-01T18:33:15.058440",
    "docker": null,
    "cuda": null,
    "args": [
        "--algo",
        "FCPO",
        "--env-id",
        "SafetyPointGoal1-v0",
        "--parallel",
        "1",
        "--total-steps",
        "10000000",
        "--device",
        "cpu",
        "--vector-env-nums",
        "20"
    ],
    "state": "running",
    "program": "/root/luoyang/newnewcode/omnisafe/examples/train_policy.py",
    "codePathLocal": "train_policy.py",
    "codePath": "examples/train_policy.py",
    "git": {
        "remote": "https://github.com/JiwenJ/omnisafe.git",
        "commit": "513aefd205b20ec5fa067f0f5db170f85d3021b5"
    },
    "email": null,
    "root": "/root/luoyang/newnewcode/omnisafe",
    "host": "taizun52",
    "username": "root",
    "executable": "/root/anaconda3/envs/rl/bin/python",
    "cpu_count": 192,
    "cpu_count_logical": 383,
    "cpu_freq": {
        "current": 2649.9595639686677,
        "min": 1500.0,
        "max": 2400.0
    },
    "cpu_freq_per_core": [
        {
            "current": 3626.46,
            "min": 1500.0,
            "max": 2400.0
        },
        {
            "current": 3623.488,
            "min": 1500.0,
            "max": 2400.0
        },
        {
            "current": 3623.489,
            "min": 1500.0,
            "max": 2400.0
        },
        {
            "current": 3623.479,
            "min": 1500.0,
            "max": 2400.0
        },
        {
            "current": 3623.478,
            "min": 1500.0,
            "max": 2400.0
        },
        {
            "current": 3623.473,
            "min": 1500.0,
            "max": 2400.0
        },
        {
            "current": 3623.47,
            "min": 1500.0,
            "max": 2400.0
        },
        {
            "current": 3624.007,
            "min": 1500.0,
            "max": 2400.0
        },
        {
            "current": 3619.983,
            "min": 1500.0,
            "max": 2400.0
        },
        {
            "current": 3619.472,
            "min": 1500.0,
            "max": 2400.0
        },
        {
            "current": 2400.0,
            "min": 1500.0,
            "max": 2400.0
        },
        {
            "current": 3623.455,
            "min": 1500.0,
            "max": 2400.0
        },
        {
            "current": 3623.453,
            "min": 1500.0,
            "max": 2400.0
        },
        {
            "current": 3623.446,
            "min": 1500.0,
            "max": 2400.0
        },
        {
            "current": 2400.0,
            "min": 1500.0,
            "max": 2400.0
        },
        {
            "current": 3623.442,
            "min": 1500.0,
            "max": 2400.0
        },
        {
            "current": 3623.439,
            "min": 1500.0,
            "max": 2400.0
        },
        {
            "current": 3623.434,
            "min": 1500.0,
            "max": 2400.0
        },
        {
            "current": 3623.434,
            "min": 1500.0,
            "max": 2400.0
        },
        {
            "current": 3623.429,
            "min": 1500.0,
            "max": 2400.0
        },
        {
            "current": 3623.427,
            "min": 1500.0,
            "max": 2400.0
        },
        {
            "current": 3623.423,
            "min": 1500.0,
            "max": 2400.0
        },
        {
            "current": 3623.423,
            "min": 1500.0,
            "max": 2400.0
        },
        {
            "current": 1900.0,
            "min": 1500.0,
            "max": 2400.0
        },
        {
            "current": 3623.418,
            "min": 1500.0,
            "max": 2400.0
        },
        {
            "current": 3623.413,
            "min": 1500.0,
            "max": 2400.0
        },
        {
            "current": 3623.41,
            "min": 1500.0,
            "max": 2400.0
        },
        {
            "current": 2400.0,
            "min": 1500.0,
            "max": 2400.0
        },
        {
            "current": 3623.406,
            "min": 1500.0,
            "max": 2400.0
        },
        {
            "current": 3623.401,
            "min": 1500.0,
            "max": 2400.0
        },
        {
            "current": 3623.399,
            "min": 1500.0,
            "max": 2400.0
        },
        {
            "current": 3623.395,
            "min": 1500.0,
            "max": 2400.0
        },
        {
            "current": 3623.392,
            "min": 1500.0,
            "max": 2400.0
        },
        {
            "current": 1500.0,
            "min": 1500.0,
            "max": 2400.0
        },
        {
            "current": 3623.39,
            "min": 1500.0,
            "max": 2400.0
        },
        {
            "current": 3623.385,
            "min": 1500.0,
            "max": 2400.0
        },
        {
            "current": 3623.383,
            "min": 1500.0,
            "max": 2400.0
        },
        {
            "current": 1500.0,
            "min": 1500.0,
            "max": 2400.0
        },
        {
            "current": 2400.0,
            "min": 1500.0,
            "max": 2400.0
        },
        {
            "current": 3623.376,
            "min": 1500.0,
            "max": 2400.0
        },
        {
            "current": 1500.0,
            "min": 1500.0,
            "max": 2400.0
        },
        {
            "current": 3623.367,
            "min": 1500.0,
            "max": 2400.0
        },
        {
            "current": 3623.364,
            "min": 1500.0,
            "max": 2400.0
        },
        {
            "current": 2400.0,
            "min": 1500.0,
            "max": 2400.0
        },
        {
            "current": 1500.0,
            "min": 1500.0,
            "max": 2400.0
        },
        {
            "current": 1500.0,
            "min": 1500.0,
            "max": 2400.0
        },
        {
            "current": 3623.353,
            "min": 1500.0,
            "max": 2400.0
        },
        {
            "current": 3623.349,
            "min": 1500.0,
            "max": 2400.0
        },
        {
            "current": 3623.351,
            "min": 1500.0,
            "max": 2400.0
        },
        {
            "current": 3623.345,
            "min": 1500.0,
            "max": 2400.0
        },
        {
            "current": 3623.346,
            "min": 1500.0,
            "max": 2400.0
        },
        {
            "current": 3623.339,
            "min": 1500.0,
            "max": 2400.0
        },
        {
            "current": 2400.0,
            "min": 1500.0,
            "max": 2400.0
        },
        {
            "current": 2400.0,
            "min": 1500.0,
            "max": 2400.0
        },
        {
            "current": 1900.0,
            "min": 1500.0,
            "max": 2400.0
        },
        {
            "current": 2400.0,
            "min": 1500.0,
            "max": 2400.0
        },
        {
            "current": 2400.0,
            "min": 1500.0,
            "max": 2400.0
        },
        {
            "current": 3623.326,
            "min": 1500.0,
            "max": 2400.0
        },
        {
            "current": 1900.0,
            "min": 1500.0,
            "max": 2400.0
        },
        {
            "current": 2400.0,
            "min": 1500.0,
            "max": 2400.0
        },
        {
            "current": 3623.317,
            "min": 1500.0,
            "max": 2400.0
        },
        {
            "current": 3623.312,
            "min": 1500.0,
            "max": 2400.0
        },
        {
            "current": 1900.0,
            "min": 1500.0,
            "max": 2400.0
        },
        {
            "current": 3623.306,
            "min": 1500.0,
            "max": 2400.0
        },
        {
            "current": 3623.306,
            "min": 1500.0,
            "max": 2400.0
        },
        {
            "current": 3623.302,
            "min": 1500.0,
            "max": 2400.0
        },
        {
            "current": 3623.301,
            "min": 1500.0,
            "max": 2400.0
        },
        {
            "current": 2400.0,
            "min": 1500.0,
            "max": 2400.0
        },
        {
            "current": 1500.0,
            "min": 1500.0,
            "max": 2400.0
        },
        {
            "current": 3623.292,
            "min": 1500.0,
            "max": 2400.0
        },
        {
            "current": 3623.291,
            "min": 1500.0,
            "max": 2400.0
        },
        {
            "current": 3623.287,
            "min": 1500.0,
            "max": 2400.0
        },
        {
            "current": 1500.0,
            "min": 1500.0,
            "max": 2400.0
        },
        {
            "current": 1500.0,
            "min": 1500.0,
            "max": 2400.0
        },
        {
            "current": 2400.0,
            "min": 1500.0,
            "max": 2400.0
        },
        {
            "current": 3623.276,
            "min": 1500.0,
            "max": 2400.0
        },
        {
            "current": 2400.0,
            "min": 1500.0,
            "max": 2400.0
        },
        {
            "current": 3623.272,
            "min": 1500.0,
            "max": 2400.0
        },
        {
            "current": 1500.0,
            "min": 1500.0,
            "max": 2400.0
        },
        {
            "current": 3623.267,
            "min": 1500.0,
            "max": 2400.0
        },
        {
            "current": 1500.0,
            "min": 1500.0,
            "max": 2400.0
        },
        {
            "current": 3623.26,
            "min": 1500.0,
            "max": 2400.0
        },
        {
            "current": 3623.258,
            "min": 1500.0,
            "max": 2400.0
        },
        {
            "current": 2400.0,
            "min": 1500.0,
            "max": 2400.0
        },
        {
            "current": 1900.0,
            "min": 1500.0,
            "max": 2400.0
        },
        {
            "current": 1500.0,
            "min": 1500.0,
            "max": 2400.0
        },
        {
            "current": 1500.0,
            "min": 1500.0,
            "max": 2400.0
        },
        {
            "current": 1500.0,
            "min": 1500.0,
            "max": 2400.0
        },
        {
            "current": 3623.244,
            "min": 1500.0,
            "max": 2400.0
        },
        {
            "current": 2400.0,
            "min": 1500.0,
            "max": 2400.0
        },
        {
            "current": 2400.0,
            "min": 1500.0,
            "max": 2400.0
        },
        {
            "current": 2400.0,
            "min": 1500.0,
            "max": 2400.0
        },
        {
            "current": 3623.235,
            "min": 1500.0,
            "max": 2400.0
        },
        {
            "current": 3623.231,
            "min": 1500.0,
            "max": 2400.0
        },
        {
            "current": 2400.0,
            "min": 1500.0,
            "max": 2400.0
        },
        {
            "current": 2400.0,
            "min": 1500.0,
            "max": 2400.0
        },
        {
            "current": 3622.236,
            "min": 1500.0,
            "max": 2400.0
        },
        {
            "current": 2400.0,
            "min": 1500.0,
            "max": 2400.0
        },
        {
            "current": 3621.925,
            "min": 1500.0,
            "max": 2400.0
        },
        {
            "current": 3621.922,
            "min": 1500.0,
            "max": 2400.0
        },
        {
            "current": 3621.922,
            "min": 1500.0,
            "max": 2400.0
        },
        {
            "current": 3622.703,
            "min": 1500.0,
            "max": 2400.0
        },
        {
            "current": 3621.922,
            "min": 1500.0,
            "max": 2400.0
        },
        {
            "current": 2400.0,
            "min": 1500.0,
            "max": 2400.0
        },
        {
            "current": 1500.0,
            "min": 1500.0,
            "max": 2400.0
        },
        {
            "current": 1500.0,
            "min": 1500.0,
            "max": 2400.0
        },
        {
            "current": 3621.912,
            "min": 1500.0,
            "max": 2400.0
        },
        {
            "current": 1500.0,
            "min": 1500.0,
            "max": 2400.0
        },
        {
            "current": 2400.0,
            "min": 1500.0,
            "max": 2400.0
        },
        {
            "current": 1500.0,
            "min": 1500.0,
            "max": 2400.0
        },
        {
            "current": 3621.904,
            "min": 1500.0,
            "max": 2400.0
        },
        {
            "current": 1500.0,
            "min": 1500.0,
            "max": 2400.0
        },
        {
            "current": 3622.67,
            "min": 1500.0,
            "max": 2400.0
        },
        {
            "current": 2400.0,
            "min": 1500.0,
            "max": 2400.0
        },
        {
            "current": 2400.0,
            "min": 1500.0,
            "max": 2400.0
        },
        {
            "current": 2400.0,
            "min": 1500.0,
            "max": 2400.0
        },
        {
            "current": 3622.665,
            "min": 1500.0,
            "max": 2400.0
        },
        {
            "current": 1500.0,
            "min": 1500.0,
            "max": 2400.0
        },
        {
            "current": 2400.0,
            "min": 1500.0,
            "max": 2400.0
        },
        {
            "current": 2400.0,
            "min": 1500.0,
            "max": 2400.0
        },
        {
            "current": 1500.0,
            "min": 1500.0,
            "max": 2400.0
        },
        {
            "current": 2400.0,
            "min": 1500.0,
            "max": 2400.0
        },
        {
            "current": 3621.883,
            "min": 1500.0,
            "max": 2400.0
        },
        {
            "current": 2400.0,
            "min": 1500.0,
            "max": 2400.0
        },
        {
            "current": 2400.0,
            "min": 1500.0,
            "max": 2400.0
        },
        {
            "current": 2400.0,
            "min": 1500.0,
            "max": 2400.0
        },
        {
            "current": 2400.0,
            "min": 1500.0,
            "max": 2400.0
        },
        {
            "current": 3622.589,
            "min": 1500.0,
            "max": 2400.0
        },
        {
            "current": 3621.875,
            "min": 1500.0,
            "max": 2400.0
        },
        {
            "current": 3621.876,
            "min": 1500.0,
            "max": 2400.0
        },
        {
            "current": 3622.612,
            "min": 1500.0,
            "max": 2400.0
        },
        {
            "current": 1500.0,
            "min": 1500.0,
            "max": 2400.0
        },
        {
            "current": 1500.0,
            "min": 1500.0,
            "max": 2400.0
        },
        {
            "current": 3621.87,
            "min": 1500.0,
            "max": 2400.0
        },
        {
            "current": 1500.0,
            "min": 1500.0,
            "max": 2400.0
        },
        {
            "current": 1900.0,
            "min": 1500.0,
            "max": 2400.0
        },
        {
            "current": 1500.0,
            "min": 1500.0,
            "max": 2400.0
        },
        {
            "current": 1500.0,
            "min": 1500.0,
            "max": 2400.0
        },
        {
            "current": 3622.6,
            "min": 1500.0,
            "max": 2400.0
        },
        {
            "current": 3622.144,
            "min": 1500.0,
            "max": 2400.0
        },
        {
            "current": 1500.0,
            "min": 1500.0,
            "max": 2400.0
        },
        {
            "current": 3622.138,
            "min": 1500.0,
            "max": 2400.0
        },
        {
            "current": 3622.588,
            "min": 1500.0,
            "max": 2400.0
        },
        {
            "current": 3621.849,
            "min": 1500.0,
            "max": 2400.0
        },
        {
            "current": 3621.851,
            "min": 1500.0,
            "max": 2400.0
        },
        {
            "current": 2663.583,
            "min": 1500.0,
            "max": 2400.0
        },
        {
            "current": 3621.847,
            "min": 1500.0,
            "max": 2400.0
        },
        {
            "current": 3621.85,
            "min": 1500.0,
            "max": 2400.0
        },
        {
            "current": 3621.842,
            "min": 1500.0,
            "max": 2400.0
        },
        {
            "current": 1500.0,
            "min": 1500.0,
            "max": 2400.0
        },
        {
            "current": 1500.0,
            "min": 1500.0,
            "max": 2400.0
        },
        {
            "current": 1500.0,
            "min": 1500.0,
            "max": 2400.0
        },
        {
            "current": 3621.837,
            "min": 1500.0,
            "max": 2400.0
        },
        {
            "current": 3621.834,
            "min": 1500.0,
            "max": 2400.0
        },
        {
            "current": 3622.103,
            "min": 1500.0,
            "max": 2400.0
        },
        {
            "current": 1900.0,
            "min": 1500.0,
            "max": 2400.0
        },
        {
            "current": 2400.0,
            "min": 1500.0,
            "max": 2400.0
        },
        {
            "current": 3621.826,
            "min": 1500.0,
            "max": 2400.0
        },
        {
            "current": 2400.0,
            "min": 1500.0,
            "max": 2400.0
        },
        {
            "current": 3621.826,
            "min": 1500.0,
            "max": 2400.0
        },
        {
            "current": 2558.507,
            "min": 1500.0,
            "max": 2400.0
        },
        {
            "current": 1500.0,
            "min": 1500.0,
            "max": 2400.0
        },
        {
            "current": 3621.823,
            "min": 1500.0,
            "max": 2400.0
        },
        {
            "current": 1900.0,
            "min": 1500.0,
            "max": 2400.0
        },
        {
            "current": 1900.0,
            "min": 1500.0,
            "max": 2400.0
        },
        {
            "current": 3622.089,
            "min": 1500.0,
            "max": 2400.0
        },
        {
            "current": 3621.817,
            "min": 1500.0,
            "max": 2400.0
        },
        {
            "current": 1900.0,
            "min": 1500.0,
            "max": 2400.0
        },
        {
            "current": 2400.0,
            "min": 1500.0,
            "max": 2400.0
        },
        {
            "current": 1900.0,
            "min": 1500.0,
            "max": 2400.0
        },
        {
            "current": 2400.0,
            "min": 1500.0,
            "max": 2400.0
        },
        {
            "current": 2400.0,
            "min": 1500.0,
            "max": 2400.0
        },
        {
            "current": 1900.0,
            "min": 1500.0,
            "max": 2400.0
        },
        {
            "current": 3621.803,
            "min": 1500.0,
            "max": 2400.0
        },
        {
            "current": 1900.0,
            "min": 1500.0,
            "max": 2400.0
        },
        {
            "current": 2400.0,
            "min": 1500.0,
            "max": 2400.0
        },
        {
            "current": 2400.0,
            "min": 1500.0,
            "max": 2400.0
        },
        {
            "current": 3621.799,
            "min": 1500.0,
            "max": 2400.0
        },
        {
            "current": 1900.0,
            "min": 1500.0,
            "max": 2400.0
        },
        {
            "current": 2400.0,
            "min": 1500.0,
            "max": 2400.0
        },
        {
            "current": 2400.0,
            "min": 1500.0,
            "max": 2400.0
        },
        {
            "current": 1500.0,
            "min": 1500.0,
            "max": 2400.0
        },
        {
            "current": 1500.0,
            "min": 1500.0,
            "max": 2400.0
        },
        {
            "current": 1900.0,
            "min": 1500.0,
            "max": 2400.0
        },
        {
            "current": 1900.0,
            "min": 1500.0,
            "max": 2400.0
        },
        {
            "current": 2400.0,
            "min": 1500.0,
            "max": 2400.0
        },
        {
            "current": 1900.0,
            "min": 1500.0,
            "max": 2400.0
        },
        {
            "current": 1500.0,
            "min": 1500.0,
            "max": 2400.0
        },
        {
            "current": 3622.036,
            "min": 1500.0,
            "max": 2400.0
        },
        {
            "current": 2400.0,
            "min": 1500.0,
            "max": 2400.0
        },
        {
            "current": 1500.0,
            "min": 1500.0,
            "max": 2400.0
        },
        {
            "current": 1500.0,
            "min": 1500.0,
            "max": 2400.0
        },
        {
            "current": 1500.0,
            "min": 1500.0,
            "max": 2400.0
        },
        {
            "current": 1900.0,
            "min": 1500.0,
            "max": 2400.0
        },
        {
            "current": 1900.0,
            "min": 1500.0,
            "max": 2400.0
        },
        {
            "current": 1500.0,
            "min": 1500.0,
            "max": 2400.0
        },
        {
            "current": 1500.0,
            "min": 1500.0,
            "max": 2400.0
        },
        {
            "current": 1500.0,
            "min": 1500.0,
            "max": 2400.0
        },
        {
            "current": 2400.0,
            "min": 1500.0,
            "max": 2400.0
        },
        {
            "current": 2400.0,
            "min": 1500.0,
            "max": 2400.0
        },
        {
            "current": 2838.374,
            "min": 1500.0,
            "max": 2400.0
        },
        {
            "current": 1500.0,
            "min": 1500.0,
            "max": 2400.0
        },
        {
            "current": 1500.0,
            "min": 1500.0,
            "max": 2400.0
        },
        {
            "current": 1900.0,
            "min": 1500.0,
            "max": 2400.0
        },
        {
            "current": 2400.0,
            "min": 1500.0,
            "max": 2400.0
        },
        {
            "current": 1500.0,
            "min": 1500.0,
            "max": 2400.0
        },
        {
            "current": 2400.0,
            "min": 1500.0,
            "max": 2400.0
        },
        {
            "current": 1500.0,
            "min": 1500.0,
            "max": 2400.0
        },
        {
            "current": 1900.0,
            "min": 1500.0,
            "max": 2400.0
        },
        {
            "current": 2400.0,
            "min": 1500.0,
            "max": 2400.0
        },
        {
            "current": 2400.0,
            "min": 1500.0,
            "max": 2400.0
        },
        {
            "current": 2400.0,
            "min": 1500.0,
            "max": 2400.0
        },
        {
            "current": 2400.0,
            "min": 1500.0,
            "max": 2400.0
        },
        {
            "current": 2400.0,
            "min": 1500.0,
            "max": 2400.0
        },
        {
            "current": 1500.0,
            "min": 1500.0,
            "max": 2400.0
        },
        {
            "current": 2400.0,
            "min": 1500.0,
            "max": 2400.0
        },
        {
            "current": 1500.0,
            "min": 1500.0,
            "max": 2400.0
        },
        {
            "current": 1500.0,
            "min": 1500.0,
            "max": 2400.0
        },
        {
            "current": 2400.0,
            "min": 1500.0,
            "max": 2400.0
        },
        {
            "current": 2400.0,
            "min": 1500.0,
            "max": 2400.0
        },
        {
            "current": 1500.0,
            "min": 1500.0,
            "max": 2400.0
        },
        {
            "current": 2400.0,
            "min": 1500.0,
            "max": 2400.0
        },
        {
            "current": 1900.0,
            "min": 1500.0,
            "max": 2400.0
        },
        {
            "current": 1500.0,
            "min": 1500.0,
            "max": 2400.0
        },
        {
            "current": 1500.0,
            "min": 1500.0,
            "max": 2400.0
        },
        {
            "current": 1900.0,
            "min": 1500.0,
            "max": 2400.0
        },
        {
            "current": 1500.0,
            "min": 1500.0,
            "max": 2400.0
        },
        {
            "current": 1500.0,
            "min": 1500.0,
            "max": 2400.0
        },
        {
            "current": 1500.0,
            "min": 1500.0,
            "max": 2400.0
        },
        {
            "current": 1500.0,
            "min": 1500.0,
            "max": 2400.0
        },
        {
            "current": 1500.0,
            "min": 1500.0,
            "max": 2400.0
        },
        {
            "current": 2400.0,
            "min": 1500.0,
            "max": 2400.0
        },
        {
            "current": 2400.0,
            "min": 1500.0,
            "max": 2400.0
        },
        {
            "current": 2400.0,
            "min": 1500.0,
            "max": 2400.0
        },
        {
            "current": 1500.0,
            "min": 1500.0,
            "max": 2400.0
        },
        {
            "current": 2400.0,
            "min": 1500.0,
            "max": 2400.0
        },
        {
            "current": 2400.0,
            "min": 1500.0,
            "max": 2400.0
        },
        {
            "current": 1500.0,
            "min": 1500.0,
            "max": 2400.0
        },
        {
            "current": 2400.0,
            "min": 1500.0,
            "max": 2400.0
        },
        {
            "current": 2400.0,
            "min": 1500.0,
            "max": 2400.0
        },
        {
            "current": 2400.0,
            "min": 1500.0,
            "max": 2400.0
        },
        {
            "current": 2400.0,
            "min": 1500.0,
            "max": 2400.0
        },
        {
            "current": 2400.0,
            "min": 1500.0,
            "max": 2400.0
        },
        {
            "current": 2400.0,
            "min": 1500.0,
            "max": 2400.0
        },
        {
            "current": 3622.884,
            "min": 1500.0,
            "max": 2400.0
        },
        {
            "current": 2400.0,
            "min": 1500.0,
            "max": 2400.0
        },
        {
            "current": 3619.498,
            "min": 1500.0,
            "max": 2400.0
        },
        {
            "current": 1500.0,
            "min": 1500.0,
            "max": 2400.0
        },
        {
            "current": 1500.0,
            "min": 1500.0,
            "max": 2400.0
        },
        {
            "current": 1500.0,
            "min": 1500.0,
            "max": 2400.0
        },
        {
            "current": 1900.0,
            "min": 1500.0,
            "max": 2400.0
        },
        {
            "current": 1900.0,
            "min": 1500.0,
            "max": 2400.0
        },
        {
            "current": 1900.0,
            "min": 1500.0,
            "max": 2400.0
        },
        {
            "current": 3622.865,
            "min": 1500.0,
            "max": 2400.0
        },
        {
            "current": 1900.0,
            "min": 1500.0,
            "max": 2400.0
        },
        {
            "current": 1900.0,
            "min": 1500.0,
            "max": 2400.0
        },
        {
            "current": 1900.0,
            "min": 1500.0,
            "max": 2400.0
        },
        {
            "current": 1900.0,
            "min": 1500.0,
            "max": 2400.0
        },
        {
            "current": 2400.0,
            "min": 1500.0,
            "max": 2400.0
        },
        {
            "current": 2400.0,
            "min": 1500.0,
            "max": 2400.0
        },
        {
            "current": 1500.0,
            "min": 1500.0,
            "max": 2400.0
        },
        {
            "current": 1500.0,
            "min": 1500.0,
            "max": 2400.0
        },
        {
            "current": 2400.0,
            "min": 1500.0,
            "max": 2400.0
        },
        {
            "current": 1900.0,
            "min": 1500.0,
            "max": 2400.0
        },
        {
            "current": 3621.788,
            "min": 1500.0,
            "max": 2400.0
        },
        {
            "current": 1500.0,
            "min": 1500.0,
            "max": 2400.0
        },
        {
            "current": 1500.0,
            "min": 1500.0,
            "max": 2400.0
        },
        {
            "current": 3621.788,
            "min": 1500.0,
            "max": 2400.0
        },
        {
            "current": 1900.0,
            "min": 1500.0,
            "max": 2400.0
        },
        {
            "current": 3621.788,
            "min": 1500.0,
            "max": 2400.0
        },
        {
            "current": 1900.0,
            "min": 1500.0,
            "max": 2400.0
        },
        {
            "current": 3621.787,
            "min": 1500.0,
            "max": 2400.0
        },
        {
            "current": 1900.0,
            "min": 1500.0,
            "max": 2400.0
        },
        {
            "current": 2400.0,
            "min": 1500.0,
            "max": 2400.0
        },
        {
            "current": 3621.787,
            "min": 1500.0,
            "max": 2400.0
        },
        {
            "current": 3621.787,
            "min": 1500.0,
            "max": 2400.0
        },
        {
            "current": 3621.79,
            "min": 1500.0,
            "max": 2400.0
        },
        {
            "current": 3621.79,
            "min": 1500.0,
            "max": 2400.0
        },
        {
            "current": 3621.789,
            "min": 1500.0,
            "max": 2400.0
        },
        {
            "current": 2400.0,
            "min": 1500.0,
            "max": 2400.0
        },
        {
            "current": 1500.0,
            "min": 1500.0,
            "max": 2400.0
        },
        {
            "current": 3621.792,
            "min": 1500.0,
            "max": 2400.0
        },
        {
            "current": 1500.0,
            "min": 1500.0,
            "max": 2400.0
        },
        {
            "current": 2400.0,
            "min": 1500.0,
            "max": 2400.0
        },
        {
            "current": 2400.0,
            "min": 1500.0,
            "max": 2400.0
        },
        {
            "current": 3621.789,
            "min": 1500.0,
            "max": 2400.0
        },
        {
            "current": 2400.0,
            "min": 1500.0,
            "max": 2400.0
        },
        {
            "current": 2400.0,
            "min": 1500.0,
            "max": 2400.0
        },
        {
            "current": 2400.0,
            "min": 1500.0,
            "max": 2400.0
        },
        {
            "current": 1900.0,
            "min": 1500.0,
            "max": 2400.0
        },
        {
            "current": 2400.0,
            "min": 1500.0,
            "max": 2400.0
        },
        {
            "current": 2400.0,
            "min": 1500.0,
            "max": 2400.0
        },
        {
            "current": 2400.0,
            "min": 1500.0,
            "max": 2400.0
        },
        {
            "current": 2400.0,
            "min": 1500.0,
            "max": 2400.0
        },
        {
            "current": 2400.0,
            "min": 1500.0,
            "max": 2400.0
        },
        {
            "current": 3621.21,
            "min": 1500.0,
            "max": 2400.0
        },
        {
            "current": 1900.0,
            "min": 1500.0,
            "max": 2400.0
        },
        {
            "current": 2400.0,
            "min": 1500.0,
            "max": 2400.0
        },
        {
            "current": 1900.0,
            "min": 1500.0,
            "max": 2400.0
        },
        {
            "current": 2400.0,
            "min": 1500.0,
            "max": 2400.0
        },
        {
            "current": 2400.0,
            "min": 1500.0,
            "max": 2400.0
        },
        {
            "current": 1900.0,
            "min": 1500.0,
            "max": 2400.0
        },
        {
            "current": 2400.0,
            "min": 1500.0,
            "max": 2400.0
        },
        {
            "current": 1500.0,
            "min": 1500.0,
            "max": 2400.0
        },
        {
            "current": 3620.988,
            "min": 1500.0,
            "max": 2400.0
        },
        {
            "current": 2400.0,
            "min": 1500.0,
            "max": 2400.0
        },
        {
            "current": 3620.989,
            "min": 1500.0,
            "max": 2400.0
        },
        {
            "current": 1500.0,
            "min": 1500.0,
            "max": 2400.0
        },
        {
            "current": 3620.989,
            "min": 1500.0,
            "max": 2400.0
        },
        {
            "current": 2400.0,
            "min": 1500.0,
            "max": 2400.0
        },
        {
            "current": 2400.0,
            "min": 1500.0,
            "max": 2400.0
        },
        {
            "current": 3621.331,
            "min": 1500.0,
            "max": 2400.0
        },
        {
            "current": 2400.0,
            "min": 1500.0,
            "max": 2400.0
        },
        {
            "current": 2400.0,
            "min": 1500.0,
            "max": 2400.0
        },
        {
            "current": 3621.331,
            "min": 1500.0,
            "max": 2400.0
        },
        {
            "current": 3620.99,
            "min": 1500.0,
            "max": 2400.0
        },
        {
            "current": 3620.989,
            "min": 1500.0,
            "max": 2400.0
        },
        {
            "current": 3620.989,
            "min": 1500.0,
            "max": 2400.0
        },
        {
            "current": 2400.0,
            "min": 1500.0,
            "max": 2400.0
        },
        {
            "current": 1900.0,
            "min": 1500.0,
            "max": 2400.0
        },
        {
            "current": 1900.0,
            "min": 1500.0,
            "max": 2400.0
        },
        {
            "current": 1500.0,
            "min": 1500.0,
            "max": 2400.0
        },
        {
            "current": 3620.992,
            "min": 1500.0,
            "max": 2400.0
        },
        {
            "current": 3620.991,
            "min": 1500.0,
            "max": 2400.0
        },
        {
            "current": 1500.0,
            "min": 1500.0,
            "max": 2400.0
        },
        {
            "current": 3620.993,
            "min": 1500.0,
            "max": 2400.0
        },
        {
            "current": 3621.102,
            "min": 1500.0,
            "max": 2400.0
        },
        {
            "current": 3620.991,
            "min": 1500.0,
            "max": 2400.0
        },
        {
            "current": 3621.103,
            "min": 1500.0,
            "max": 2400.0
        },
        {
            "current": 1500.0,
            "min": 1500.0,
            "max": 2400.0
        },
        {
            "current": 1500.0,
            "min": 1500.0,
            "max": 2400.0
        },
        {
            "current": 1500.0,
            "min": 1500.0,
            "max": 2400.0
        },
        {
            "current": 1500.0,
            "min": 1500.0,
            "max": 2400.0
        },
        {
            "current": 2400.0,
            "min": 1500.0,
            "max": 2400.0
        },
        {
            "current": 1500.0,
            "min": 1500.0,
            "max": 2400.0
        },
        {
            "current": 3597.715,
            "min": 1500.0,
            "max": 2400.0
        },
        {
            "current": 3338.915,
            "min": 1500.0,
            "max": 2400.0
        },
        {
            "current": 3642.184,
            "min": 1500.0,
            "max": 2400.0
        },
        {
            "current": 2886.569,
            "min": 1500.0,
            "max": 2400.0
        },
        {
            "current": 3619.891,
            "min": 1500.0,
            "max": 2400.0
        },
        {
            "current": 3590.965,
            "min": 1500.0,
            "max": 2400.0
        },
        {
            "current": 3620.987,
            "min": 1500.0,
            "max": 2400.0
        },
        {
            "current": 3429.315,
            "min": 1500.0,
            "max": 2400.0
        },
        {
            "current": 1500.0,
            "min": 1500.0,
            "max": 2400.0
        },
        {
            "current": 1900.0,
            "min": 1500.0,
            "max": 2400.0
        },
        {
            "current": 2400.0,
            "min": 1500.0,
            "max": 2400.0
        },
        {
            "current": 3621.103,
            "min": 1500.0,
            "max": 2400.0
        },
        {
            "current": 3620.99,
            "min": 1500.0,
            "max": 2400.0
        },
        {
            "current": 1500.0,
            "min": 1500.0,
            "max": 2400.0
        },
        {
            "current": 1900.0,
            "min": 1500.0,
            "max": 2400.0
        },
        {
            "current": 1900.0,
            "min": 1500.0,
            "max": 2400.0
        },
        {
            "current": 2400.0,
            "min": 1500.0,
            "max": 2400.0
        },
        {
            "current": 1900.0,
            "min": 1500.0,
            "max": 2400.0
        },
        {
            "current": 1900.0,
            "min": 1500.0,
            "max": 2400.0
        },
        {
            "current": 3621.324,
            "min": 1500.0,
            "max": 2400.0
        },
        {
            "current": 3620.992,
            "min": 1500.0,
            "max": 2400.0
        },
        {
            "current": 2400.0,
            "min": 1500.0,
            "max": 2400.0
        },
        {
            "current": 1900.0,
            "min": 1500.0,
            "max": 2400.0
        },
        {
            "current": 1900.0,
            "min": 1500.0,
            "max": 2400.0
        },
        {
            "current": 3620.99,
            "min": 1500.0,
            "max": 2400.0
        },
        {
            "current": 1500.0,
            "min": 1500.0,
            "max": 2400.0
        },
        {
            "current": 3620.99,
            "min": 1500.0,
            "max": 2400.0
        },
        {
            "current": 1900.0,
            "min": 1500.0,
            "max": 2400.0
        },
        {
            "current": 3620.99,
            "min": 1500.0,
            "max": 2400.0
        },
        {
            "current": 2400.0,
            "min": 1500.0,
            "max": 2400.0
        },
        {
            "current": 3620.99,
            "min": 1500.0,
            "max": 2400.0
        },
        {
            "current": 3621.098,
            "min": 1500.0,
            "max": 2400.0
        },
        {
            "current": 1900.0,
            "min": 1500.0,
            "max": 2400.0
        },
        {
            "current": 1900.0,
            "min": 1500.0,
            "max": 2400.0
        },
        {
            "current": 3620.991,
            "min": 1500.0,
            "max": 2400.0
        },
        {
            "current": 1500.0,
            "min": 1500.0,
            "max": 2400.0
        },
        {
            "current": 3621.102,
            "min": 1500.0,
            "max": 2400.0
        },
        {
            "current": 3621.101,
            "min": 1500.0,
            "max": 2400.0
        },
        {
            "current": 2400.0,
            "min": 1500.0,
            "max": 2400.0
        },
        {
            "current": 3620.99,
            "min": 1500.0,
            "max": 2400.0
        },
        {
            "current": 2400.0,
            "min": 1500.0,
            "max": 2400.0
        },
        {
            "current": 1900.0,
            "min": 1500.0,
            "max": 2400.0
        },
        {
            "current": 3620.991,
            "min": 1500.0,
            "max": 2400.0
        },
        {
            "current": 3621.804,
            "min": 1500.0,
            "max": 2400.0
        },
        {
            "current": 1900.0,
            "min": 1500.0,
            "max": 2400.0
        },
        {
            "current": 3620.99,
            "min": 1500.0,
            "max": 2400.0
        },
        {
            "current": 3621.326,
            "min": 1500.0,
            "max": 2400.0
        },
        {
            "current": 3620.989,
            "min": 1500.0,
            "max": 2400.0
        }
    ],
    "disk": {
        "/": {
            "total": 491.082275390625,
            "used": 108.11578750610352
        }
    },
    "gpu": "NVIDIA RTX A6000",
    "gpu_count": 4,
    "gpu_devices": [
        {
            "name": "NVIDIA RTX A6000",
            "memory_total": 51527024640
        },
        {
            "name": "NVIDIA RTX A6000",
            "memory_total": 51527024640
        },
        {
            "name": "NVIDIA RTX A6000",
            "memory_total": 51527024640
        },
        {
            "name": "NVIDIA RTX A6000",
            "memory_total": 51527024640
        }
    ],
    "memory": {
        "total": 1007.5055770874023
    }
}
